PyEngine
PyForge
